certbot_dns_ecenter/__init__.py
certbot_dns_ecenter/__version__.py
certbot_dns_ecenter/api_ecenter.py
certbot_dns_ecenter/dns_ecenter.py
tests/__init__.py
tests/conftest.py
tests/test_dns_ecenter.py
certbot_dns_ecenter-0.2.1.dist-info/METADATA
certbot_dns_ecenter-0.2.1.dist-info/WHEEL
certbot_dns_ecenter-0.2.1.dist-info/entry_points.txt
certbot_dns_ecenter-0.2.1.dist-info/top_level.txt
certbot_dns_ecenter-0.2.1.dist-info/RECORD
