Metadata-Version: 2.4
Name: certbot-dns-ecenter
Version: 0.2.1
Summary: Edge-Center DNS Authenticator plugin for Certbot
Home-page: https://github.com/Edge-Center/ec-dns-certbot-plugin
Author: Edge-Center
Author-email: support@edgecenter.ru
License: Apache License 2.0
Requires-Python: >=3.8
Requires-Dist: certbot>=1.23.0
Requires-Dist: setuptools>=39.0.1
Provides-Extra: docs
Requires-Dist: Sphinx>=1.0; extra == "docs"
Requires-Dist: sphinx_rtd_theme; extra == "docs"
Dynamic: author
Dynamic: author-email
Dynamic: description
Dynamic: description-content-type
Dynamic: home-page
Dynamic: license
Dynamic: provides-extra
Dynamic: requires-dist
Dynamic: requires-python
Dynamic: summary
